<?xml version="1.0" encoding="UTF-8"?>
<metadata xml:lang="en"><Esri><CreaDate>20260210</CreaDate><CreaTime>12180900</CreaTime><ArcGISFormat>1.0</ArcGISFormat><SyncOnce>TRUE</SyncOnce><ModDate>20260210</ModDate><ModTime>130931</ModTime></Esri><toolbox name="StripSdeCredentials" alias="stripsdecreds"><arcToolboxHelpPath>e:\sw_nt\arcgis\desktop10.8\Help\gp</arcToolboxHelpPath><toolsets/></toolbox><dataIdInfo><idCitation><resTitle>StripSdeCredentials</resTitle></idCitation></dataIdInfo><distInfo><distributor><distorFormat><formatName>ArcToolbox Toolbox</formatName></distorFormat></distributor></distInfo></metadata>
